haut_scanner/__init__.py
haut_scanner/jwglxt.py
haut_scanner-0.1.0.dist-info/METADATA
haut_scanner-0.1.0.dist-info/WHEEL
haut_scanner-0.1.0.dist-info/entry_points.txt
haut_scanner-0.1.0.dist-info/licenses/LICENSE
haut_scanner-0.1.0.dist-info/RECORD
