Metadata-Version: 2.4
Name: haut_scanner
Version: 0.1.0
Summary: Asynchronous scanning utilities for discovering HAUT services, starting with the JWGLXT portal.
License-File: LICENSE
Keywords: asyncio,haut,jwglxt,network,scanner
Classifier: Programming Language :: Python
Classifier: Programming Language :: Python :: 3
Classifier: Programming Language :: Python :: 3.11
Classifier: Topic :: Internet
Classifier: Topic :: System :: Networking
Requires-Python: >=3.11
Requires-Dist: aiohttp>=3.12.13
Requires-Dist: beautifulsoup4>=4.13.0
Requires-Dist: hatch>=1.15.1
